flake8_todo_ticket/__init__.py
flake8_todo_ticket/metadata.py
flake8_todo_ticket-0.1.0.dist-info/LICENSE
flake8_todo_ticket-0.1.0.dist-info/METADATA
flake8_todo_ticket-0.1.0.dist-info/WHEEL
flake8_todo_ticket-0.1.0.dist-info/entry_points.txt
flake8_todo_ticket-0.1.0.dist-info/top_level.txt
flake8_todo_ticket-0.1.0.dist-info/RECORD
