Metadata-Version: 2.1
Name: flake8-todo-ticket
Version: 0.1.0
Summary: Enforce ownership and ticketing of TODO notes.
Home-page: https://github.com/tommilligan/flake8-todo-ticket
Author: Tom Milligan
Author-email: tommilligan@users.noreply.github.com
License: Apache-2.0
Keywords: flake8 plugin todo ticket owner
Platform: UNKNOWN
Classifier: Framework :: Flake8
Classifier: Intended Audience :: Developers
Classifier: Development Status :: 5 - Production/Stable
Classifier: Operating System :: OS Independent
Classifier: License :: OSI Approved :: Apache Software License
Classifier: Programming Language :: Python
Classifier: Programming Language :: Python :: 3
Classifier: Programming Language :: Python :: 3.6
Classifier: Programming Language :: Python :: 3.7
Classifier: Programming Language :: Python :: 3.8
Classifier: Topic :: Software Development :: Quality Assurance
